examples/__init__.py
examples/plot_qrf_conformalized_intervals.py
examples/plot_qrf_custom_functions.py
examples/plot_qrf_extrapolation.py
examples/plot_qrf_huggingface_inference.py
examples/plot_qrf_interpolation_methods.py
examples/plot_qrf_multitarget.py
examples/plot_qrf_prediction_intervals.py
examples/plot_qrf_predictions.py
examples/plot_qrf_proximity_counts.py
examples/plot_qrf_quantile_ranks.py
examples/plot_qrf_treeshap_explanations.py
examples/plot_qrf_vs_rf_predictions.py
quantile_forest/__init__.py
quantile_forest/_min_dependencies.py
quantile_forest/_quantile_forest.py
quantile_forest/_quantile_forest_fast.cp313-win_amd64.pyd
quantile_forest/_quantile_forest_fast.cpp
quantile_forest/_quantile_forest_fast.pxd
quantile_forest/_quantile_forest_fast.pyx
quantile_forest/_utils.cp313-win_amd64.pyd
quantile_forest/_utils.cpp
quantile_forest/_utils.pxd
quantile_forest/_utils.pyx
quantile_forest/version.py
quantile_forest/version.txt
quantile_forest/tests/__init__.py
quantile_forest/tests/test_quantile_forest.py
quantile_forest/tests/test_utils.py
quantile_forest-1.4.1.dist-info/licenses/LICENSE
quantile_forest-1.4.1.dist-info/METADATA
quantile_forest-1.4.1.dist-info/WHEEL
quantile_forest-1.4.1.dist-info/top_level.txt
quantile_forest-1.4.1.dist-info/RECORD
