Metadata-Version: 2.4
Name: quantile-forest
Version: 1.4.1
Summary: Quantile regression forests compatible with scikit-learn.
Author: Zillow Group AI Team
Maintainer: Zillow Group AI Team
License-Expression: Apache-2.0
Project-URL: Documentation, https://zillow.github.io/quantile-forest
Project-URL: Source, https://github.com/zillow/quantile-forest
Project-URL: Tracker, https://github.com/zillow/quantile-forest/issues
Classifier: Intended Audience :: Science/Research
Classifier: Intended Audience :: Developers
Classifier: Programming Language :: Python
Classifier: Topic :: Software Development
Classifier: Topic :: Scientific/Engineering
Classifier: Operating System :: Microsoft :: Windows
Classifier: Operating System :: POSIX
Classifier: Operating System :: Unix
Classifier: Operating System :: MacOS
Classifier: Programming Language :: Python :: 3.9
Classifier: Programming Language :: Python :: 3.10
Classifier: Programming Language :: Python :: 3.11
Classifier: Programming Language :: Python :: 3.12
Classifier: Programming Language :: Python :: 3.13
Classifier: Programming Language :: Python :: Implementation :: CPython
Requires-Python: >=3.9
License-File: LICENSE
Requires-Dist: numpy>=1.23
Requires-Dist: scipy>=1.4
Requires-Dist: scikit-learn>=1.5
Dynamic: license-file
